deprecate_cmsplugin_filer/__init__.py
deprecate_cmsplugin_filer/apps.py
deprecate_cmsplugin_filer/migrations/__init__.py
deprecate_cmsplugin_filer/migrations/migration_filer_deprecation_move.py
deprecate_cmsplugin_filer-0.1.0.dist-info/WHEEL
deprecate_cmsplugin_filer-0.1.0.dist-info/METADATA
deprecate_cmsplugin_filer-0.1.0.dist-info/RECORD
