Metadata-Version: 2.1
Name: deprecate-cmsplugin-filer
Version: 0.1.0
Summary: A small app with a migration for converting deprecated cmsplugin-filer objects to djangocms plugin objects.
Home-page: https://github.com/ImaginaryLandscape/deprecate_cmsplugin_filer
License: MIT
Author: Imagescape
Author-email: info@imagescape.com
Classifier: License :: OSI Approved :: MIT License
Classifier: Programming Language :: Python :: 2
Classifier: Programming Language :: Python :: 2.7
Classifier: Programming Language :: Python :: 3
Classifier: Programming Language :: Python :: 3.4
Classifier: Programming Language :: Python :: 3.5
Classifier: Programming Language :: Python :: 3.6
Classifier: Programming Language :: Python :: 3.7
Classifier: Programming Language :: Python :: 3.8
Classifier: Programming Language :: Python :: 3.9
